cryptoadvance/specter/__init__.py
cryptoadvance/specter/__main__.py
cryptoadvance/specter/_version.py
cryptoadvance/specter/config.py
cryptoadvance/specter/device.py
cryptoadvance/specter/gunicorn.py
cryptoadvance/specter/helpers.py
cryptoadvance/specter/htmlsafebabel.py
cryptoadvance/specter/hwi_rpc.py
cryptoadvance/specter/hwi_server.py
cryptoadvance/specter/internal_node.py
cryptoadvance/specter/key.py
cryptoadvance/specter/node.py
cryptoadvance/specter/persistence.py
cryptoadvance/specter/rpc.py
cryptoadvance/specter/server.py
cryptoadvance/specter/specter.py
cryptoadvance/specter/specter_error.py
cryptoadvance/specter/tor_daemon.py
cryptoadvance/specter/user.py
cryptoadvance/specter/api/__init__.py
cryptoadvance/specter/api/security.py
cryptoadvance/specter/api/views.py
cryptoadvance/specter/api/rest/__init__.py
cryptoadvance/specter/api/rest/api.py
cryptoadvance/specter/api/rest/base.py
cryptoadvance/specter/api/rest/resource_healthz.py
cryptoadvance/specter/api/rest/resource_jwt.py
cryptoadvance/specter/api/rest/resource_psbt.py
cryptoadvance/specter/api/rest/resource_specter.py
cryptoadvance/specter/api/rest/resource_txlist.py
cryptoadvance/specter/api/templates/api.html
cryptoadvance/specter/cli/__init__.py
cryptoadvance/specter/cli/cli_ext.py
cryptoadvance/specter/cli/cli_gunicorn.py
cryptoadvance/specter/cli/cli_noded.py
cryptoadvance/specter/cli/cli_server.py
cryptoadvance/specter/cli/utils.py
cryptoadvance/specter/commands/psbt_creator.py
cryptoadvance/specter/commands/utxo_scanner.py
cryptoadvance/specter/devices/__init__.py
cryptoadvance/specter/devices/bitbox02.py
cryptoadvance/specter/devices/bitcoin_core.py
cryptoadvance/specter/devices/cobo.py
cryptoadvance/specter/devices/coldcard.py
cryptoadvance/specter/devices/elements_core.py
cryptoadvance/specter/devices/generic.py
cryptoadvance/specter/devices/hwi_device.py
cryptoadvance/specter/devices/jade.py
cryptoadvance/specter/devices/keepkey.py
cryptoadvance/specter/devices/keystone.py
cryptoadvance.specter-2.1.1.dist-info/LICENSE
cryptoadvance.specter-2.1.1.dist-info/METADATA
cryptoadvance.specter-2.1.1.dist-info/WHEEL
cryptoadvance.specter-2.1.1.dist-info/entry_points.txt
cryptoadvance.specter-2.1.1.dist-info/top_level.txt
cryptoadvance.specter-2.1.1.dist-info/RECORD
