Metadata-Version: 2.1
Name: cryptoadvance.specter
Version: 2.1.1
Summary: A GUI for Bitcoin Core & Electrum optimised to work with airgapped hardware wallets
Author: Stepan Snigirev, k9ert
License: MIT License
Project-URL: Homepage, https://github.com/cryptoadvance/specter-desktop
Project-URL: Documentation, https://docs.specter.solutions/desktop/
Project-URL: Changes, https://docs.specter.solutions/desktop/release-notes/
Classifier: Programming Language :: Python :: 3
Classifier: License :: OSI Approved :: MIT License
Classifier: Operating System :: OS Independent
Classifier: Framework :: Flask
Requires-Python: <4.0,>=3.7
License-File: LICENSE
Requires-Dist: certifi==2024.6.2
Requires-Dist: Click==8.1.7
Requires-Dist: Flask==2.2.5
Requires-Dist: Flask-Babel==3.1.0
Requires-Dist: Flask-Cors==3.0.10
Requires-Dist: Flask-Login==0.6.3
Requires-Dist: Flask-RESTful==0.3.10
Requires-Dist: Flask-HTTPAuth==4.8.0
Requires-Dist: hwi==2.4.0
Requires-Dist: python-dotenv==0.21.1
Requires-Dist: requests==2.26.0
Requires-Dist: pysocks==1.7.1
Requires-Dist: six==1.16.0
Requires-Dist: stem==1.8.0
Requires-Dist: embit==0.6.1
Requires-Dist: psutil==5.9.0
Requires-Dist: pyopenssl==24.1.0
Requires-Dist: flask-wtf==1.2.1
Requires-Dist: pgpy==0.6.0
Requires-Dist: cbor2==5.4.6
Requires-Dist: mnemonic==0.21
Requires-Dist: cryptography==42.0.7
Requires-Dist: Flask-APScheduler==1.12.4
Requires-Dist: gunicorn==20.1.0
Requires-Dist: simple-websocket==0.8.1
Requires-Dist: protobuf==4.23.3
Requires-Dist: PyJWT==2.4.0
Requires-Dist: pytimeparse==1.1.8
Requires-Dist: psycopg2-binary==2.9.5
Requires-Dist: aioitertools==0.11.0
Requires-Dist: cryptoadvance-liquidissuer==0.2.4
Requires-Dist: specterext-exfund==0.1.7
Requires-Dist: specterext-faucet==0.1.2
Requires-Dist: cryptoadvance.spectrum==0.6.7
Requires-Dist: specterext-stacktrack==0.3.0
Requires-Dist: greenlet==2.0.2
Provides-Extra: gendownloadpage
Requires-Dist: markdown==3.3.7; extra == "gendownloadpage"
Provides-Extra: test
Requires-Dist: black==22.3.0; extra == "test"
Requires-Dist: pre-commit==2.13.0; extra == "test"
Requires-Dist: pip-tools==6.13; extra == "test"
Requires-Dist: pytest==7.1.2; extra == "test"
Requires-Dist: PySocks==1.7.1; extra == "test"
Requires-Dist: pytest-cov==2.10.1; extra == "test"
Requires-Dist: mock==4.0.2; extra == "test"
Requires-Dist: python-gitlab==2.10.1; extra == "test"
Requires-Dist: requests==2.26.0; extra == "test"
